<?xml version="1.0" encoding="UTF-8"?>
<!--
  QuoteAssist Outlook add-in manifest (stub).
  Manifest v2 / ReadWriteItem is finalised in Phase 2 (CC-05/06 + Graph wiring).
  Replace the placeholder GUID, URLs and Entra app registration before sideload.
-->
<OfficeApp
  xmlns="http://schemas.microsoft.com/office/appforoffice/1.1"
  xmlns:xsi="http://www.w3.org/2001/XMLSchema-instance"
  xmlns:bt="http://schemas.microsoft.com/office/officeappbasictypes/1.0"
  xmlns:mailappor="http://schemas.microsoft.com/office/mailappversionoverrides/1.0"
  xsi:type="MailApp">
  <Id>00000000-0000-0000-0000-000000000000</Id>
  <Version>0.1.0</Version>
  <ProviderName>QuoteAssist</ProviderName>
  <DefaultLocale>en-US</DefaultLocale>
  <DisplayName DefaultValue="QuoteAssist" />
  <Description DefaultValue="Turn an inbound enquiry into a policy-checked quotation." />
  <Hosts>
    <Host Name="Mailbox" />
  </Hosts>
  <Requirements>
    <Sets>
      <Set Name="Mailbox" MinVersion="1.5" />
    </Sets>
  </Requirements>
  <FormSettings>
    <Form xsi:type="ItemRead">
      <DesktopSettings>
        <SourceLocation DefaultValue="https://localhost:3000/taskpane.html" />
        <RequestedHeight>450</RequestedHeight>
      </DesktopSettings>
    </Form>
  </FormSettings>
  <Permissions>ReadWriteItem</Permissions>
  <Rule xsi:type="RuleCollection" Mode="Or">
    <Rule xsi:type="ItemIs" ItemType="Message" FormType="Read" />
  </Rule>
</OfficeApp>
